{
  "_class": "text",
  "attributedString": {
    "_class": "attributedString",
    "attributes": [
      {
        "_class": "stringAttribute",
        "attributes": {
          "MSAttributedStringColorAttribute": {
            "_class": "color",
            "alpha": 1,
            "blue": 0.2,
            "green": 0.2,
            "red": 0.2
          },
          "MSAttributedStringFontAttribute": {
            "_class": "fontDescriptor",
            "attributes": {
              "name": "OpenSans-SemiBold",
              "size": 21.32999992370605
            }
          },
          "paragraphStyle": {
            "_class": "paragraphStyle"
          },
          "textStyleVerticalAlignmentKey": 0
        },
        "length": 9,
        "location": 0
      }
    ],
    "string": "Control 1"
  },
  "automaticallyDrawOnUnderlyingPath": false,
  "do_objectID": "42970B24-1C60-4E2D-88A7-5D55927A8CF1",
  "dontSynchroniseWithSymbol": false,
  "exportOptions": {
    "_class": "exportOptions",
    "do_objectID": "6CD710CA-6AF8-4B98-9A21-874DFE78530D",
    "exportFormats": [
    ],
    "includedLayerIds": [
    ],
    "layerOptions": 0,
    "shouldTrim": false
  },
  "frame": {
    "_class": "rect",
    "constrainProportions": false,
    "do_objectID": "AAC204A5-81C9-4AA4-B734-163A4326E55B",
    "height": 29,
    "width": 268,
    "x": 23,
    "y": 17
  },
  "glyphBounds": "{{1, 6}, {89, 18}}",
  "isFlippedHorizontal": false,
  "isFlippedVertical": false,
  "isLocked": false,
  "isVisible": true,
  "layerListExpandedType": 0,
  "lineSpacingBehaviour": 2,
  "name": "Control 1",
  "nameIsFixed": false,
  "resizingConstraint": 47,
  "resizingType": 0,
  "rotation": 0,
  "shouldBreakMaskChain": false,
  "style": {
    "_class": "style",
    "do_objectID": "9D1FE273-AD0A-495E-AABA-6DCD415033C5",
    "endDecorationType": 0,
    "miterLimit": 10,
    "sharedObjectID": "566B18D2-EE6A-4265-826E-862A37CBF956",
    "startDecorationType": 0,
    "textStyle": {
      "_class": "textStyle",
      "do_objectID": "63ABEC48-2AC8-4D7F-8ECB-89BFFCC35635",
      "encodedAttributes": {
        "MSAttributedStringColorAttribute": {
          "_class": "color",
          "alpha": 1,
          "blue": 0.2,
          "green": 0.2,
          "red": 0.2
        },
        "MSAttributedStringFontAttribute": {
          "_class": "fontDescriptor",
          "attributes": {
            "name": "OpenSans-SemiBold",
            "size": 21.32999992370605
          }
        },
        "paragraphStyle": {
          "_class": "paragraphStyle"
        },
        "textStyleVerticalAlignmentKey": 0
      },
      "verticalAlignment": 0
    }
  },
  "textBehaviour": 1,
  "userInfo": {
    "com.animaapp.stc-sketch-plugin": {
      "kModelPropertiesKey": {
        "isAutoWidth": 0
      }
    }
  }
}