{
  "_class": "symbolInstance",
  "do_objectID": "B5B53767-B18B-44ED-AB03-C4D574E73AB1",
  "exportOptions": {
    "_class": "exportOptions",
    "do_objectID": "BAACED46-3554-4F6A-A3DB-FD3861DB95FB",
    "exportFormats": [
    ],
    "includedLayerIds": [
    ],
    "layerOptions": 0,
    "shouldTrim": false
  },
  "frame": {
    "_class": "rect",
    "constrainProportions": false,
    "do_objectID": "E6571640-A232-45B0-9926-9C3010727251",
    "height": 48,
    "width": 1440,
    "x": 0,
    "y": 128
  },
  "horizontalSpacing": 0,
  "isFlippedHorizontal": false,
  "isFlippedVertical": false,
  "isLocked": false,
  "isVisible": true,
  "layerListExpandedType": 0,
  "name": "menu/procesos 1",
  "nameIsFixed": false,
  "overrideValues": [
  ],
  "resizingConstraint": 63,
  "resizingType": 0,
  "rotation": 0,
  "scale": 1,
  "shouldBreakMaskChain": false,
  "style": {
    "_class": "style",
    "do_objectID": "9C74E91F-196A-459C-8715-DB21AD7B6157",
    "endDecorationType": 0,
    "miterLimit": 10,
    "startDecorationType": 0
  },
  "symbolID": "D7DEE68D-ADA1-4C62-8CDE-88D705E3A18B",
  "userInfo": {
    "com.animaapp.stc-sketch-plugin": {
      "kModelPropertiesKey": {
      }
    }
  },
  "verticalSpacing": 0
}