{
  "_class": "shapePath",
  "booleanOperation": -1,
  "do_objectID": "DDE838F2-D402-4BDF-830E-587AF8DC1BCC",
  "edited": true,
  "exportOptions": {
    "_class": "exportOptions",
    "do_objectID": "D5C3C2F9-0494-473B-9B37-1FD60C61BE95",
    "exportFormats": [
    ],
    "includedLayerIds": [
    ],
    "layerOptions": 0,
    "shouldTrim": false
  },
  "frame": {
    "_class": "rect",
    "constrainProportions": false,
    "do_objectID": "08DF1029-E7B0-4FBB-848D-A04A3FD327B8",
    "height": 2.000000000000001,
    "width": 189,
    "x": 0,
    "y": 0
  },
  "isClosed": false,
  "isFlippedHorizontal": false,
  "isFlippedVertical": false,
  "isLocked": false,
  "isVisible": true,
  "layerListExpandedType": 0,
  "name": "Path",
  "nameIsFixed": false,
  "pointRadiusBehaviour": 1,
  "points": [
    {
      "_class": "curvePoint",
      "cornerRadius": 0,
      "curveFrom": "{0.0026455026455026454, 0.74999999999999911}",
      "curveMode": 1,
      "curveTo": "{0.0026455026455026454, 0.74999999999999911}",
      "hasCurveFrom": false,
      "hasCurveTo": false,
      "point": "{0, 0.50000000000000011}"
    },
    {
      "_class": "curvePoint",
      "cornerRadius": 0,
      "curveFrom": "{0.0079365079365079343, 1.2499999999999982}",
      "curveMode": 1,
      "curveTo": "{0.0079365079365079343, 1.2499999999999982}",
      "hasCurveFrom": false,
      "hasCurveTo": false,
      "point": "{0.99999999999999989, 0.49999999999999978}"
    }
  ],
  "resizingConstraint": 63,
  "resizingType": 0,
  "rotation": 0,
  "shouldBreakMaskChain": false
}