{
  "_class": "shapeGroup",
  "clippingMaskMode": 0,
  "do_objectID": "D5B8BF64-D19B-4ECA-BB70-34ED099D0AF1",
  "exportOptions": {
    "_class": "exportOptions",
    "do_objectID": "5CD2D913-DC16-4C74-B04E-AA205AA6B52F",
    "exportFormats": [
    ],
    "includedLayerIds": [
    ],
    "layerOptions": 0,
    "shouldTrim": false
  },
  "frame": {
    "_class": "rect",
    "constrainProportions": false,
    "do_objectID": "83A50B41-40C9-4CD7-8F58-D7FD764E996C",
    "height": 36,
    "width": 2,
    "x": 304,
    "y": 1
  },
  "hasClickThrough": false,
  "hasClippingMask": false,
  "isFlippedHorizontal": false,
  "isFlippedVertical": false,
  "isLocked": false,
  "isVisible": true,
  "layerListExpandedType": 1,
  "layers": [
    {
      "class": "shapePath",
      "id": "BB362401-3E71-4E2E-BC74-84C075980C03"
    }
  ],
  "name": "Line 2 Copy",
  "nameIsFixed": false,
  "resizingConstraint": 63,
  "resizingType": 0,
  "rotation": 0,
  "shouldBreakMaskChain": false,
  "style": {
    "_class": "style",
    "blur": {
      "_class": "blur",
      "center": "{0.5, 0.5}",
      "do_objectID": "25FE64D9-7E38-4928-9BE7-7AA995E9E665",
      "isEnabled": false,
      "motionAngle": 0,
      "radius": 10.23264,
      "type": 0
    },
    "borders": [
      {
        "_class": "border",
        "color": {
          "_class": "color",
          "alpha": 1,
          "blue": 0.5529411764705879,
          "green": 0.06666666666666662,
          "red": 0.9176470588235294
        },
        "fillType": 0,
        "isEnabled": true,
        "position": 0,
        "thickness": 1
      }
    ],
    "do_objectID": "B48BAC19-6D9A-4F40-B2D4-510C16620A08",
    "endDecorationType": 0,
    "miterLimit": 10,
    "sharedObjectID": "89D7F5FA-C9A0-4F15-8EA7-8CA815F0D45B",
    "startDecorationType": 0
  },
  "userInfo": {
    "com.animaapp.stc-sketch-plugin": {
      "kModelPropertiesKey": {
      }
    }
  },
  "windingRule": 1
}