{
  "_class": "group",
  "do_objectID": "821F85D8-B8DE-4FFD-A233-224FF7435A4D",
  "exportOptions": {
    "_class": "exportOptions",
    "do_objectID": "C8620E27-9F29-4447-9341-A28F03007289",
    "exportFormats": [
    ],
    "includedLayerIds": [
    ],
    "layerOptions": 0,
    "shouldTrim": false
  },
  "frame": {
    "_class": "rect",
    "constrainProportions": false,
    "do_objectID": "1582D3D7-6FB2-4A45-A904-EB669778CD09",
    "height": 54,
    "width": 1440,
    "x": 0,
    "y": 0
  },
  "hasClickThrough": false,
  "isFlippedHorizontal": false,
  "isFlippedVertical": false,
  "isLocked": false,
  "isVisible": true,
  "layerListExpandedType": 2,
  "layers": [
    {
      "class": "bitmap",
      "id": "CD7709F2-F678-43B5-998D-14BAE9696962"
    }
  ],
  "name": "grid 1200",
  "nameIsFixed": true,
  "resizingConstraint": 63,
  "resizingType": 0,
  "rotation": 0,
  "shouldBreakMaskChain": false,
  "style": {
    "_class": "style",
    "contextSettings": {
      "_class": "graphicsContextSettings",
      "blendMode": 0,
      "do_objectID": "28C7E11C-79FC-4A4F-B646-463FEDE5D9A5",
      "opacity": 0.5128264925373134
    },
    "do_objectID": "B49C7373-50B4-431B-8D04-5EC035A6CC8B",
    "endDecorationType": 0,
    "miterLimit": 10,
    "startDecorationType": 0
  },
  "userInfo": {
    "com.animaapp.stc-sketch-plugin": {
      "kModelPropertiesKey": {
      }
    }
  }
}