{
  "_class": "group",
  "do_objectID": "0C666D46-AAD9-433A-A55C-869BCFCC3AE7",
  "exportOptions": {
    "_class": "exportOptions",
    "do_objectID": "0C077502-DF06-49DF-BA61-78503A7DF455",
    "exportFormats": [
    ],
    "includedLayerIds": [
    ],
    "layerOptions": 0,
    "shouldTrim": false
  },
  "frame": {
    "_class": "rect",
    "constrainProportions": false,
    "do_objectID": "27B30AAF-7E1D-41D4-AE6E-9DDAFD4CABB5",
    "height": 36,
    "width": 28,
    "x": 26,
    "y": 16
  },
  "hasClickThrough": false,
  "isFlippedHorizontal": false,
  "isFlippedVertical": false,
  "isLocked": false,
  "isVisible": true,
  "layerListExpandedType": 1,
  "layers": [
    {
      "class": "group",
      "id": "0C0CB9D9-3143-425F-9F7B-3B0EDEF6933F"
    },
    {
      "class": "group",
      "id": "60AC3732-9473-4C3D-BD39-2763B640B905"
    },
    {
      "class": "shapeGroup",
      "id": "C1827677-6465-48E8-AE8C-C22F3F410E7D"
    },
    {
      "class": "symbolInstance",
      "id": "103817D8-74BC-4B84-9C1E-00CB772AE039"
    }
  ],
  "name": "doc_but",
  "nameIsFixed": true,
  "resizingConstraint": 63,
  "resizingType": 0,
  "rotation": 0,
  "shouldBreakMaskChain": false,
  "style": {
    "_class": "style",
    "blur": {
      "_class": "blur",
      "center": "{0.5, 0.5}",
      "do_objectID": "609B185A-E0C5-4A75-93F9-3B0A2B9E52AE",
      "isEnabled": false,
      "motionAngle": 0,
      "radius": 4,
      "type": 0
    },
    "do_objectID": "988EC846-3681-4C8B-96F5-ADD61857356F",
    "endDecorationType": 0,
    "miterLimit": 10,
    "startDecorationType": 0
  },
  "userInfo": {
    "com.animaapp.stc-sketch-plugin": {
      "kModelPropertiesKey": {
      }
    }
  }
}