{
  "_class": "shapePath",
  "booleanOperation": -1,
  "do_objectID": "7D0F4CAA-AE1D-49E8-9CF6-56F782813EE9",
  "edited": true,
  "exportOptions": {
    "_class": "exportOptions",
    "do_objectID": "96280433-C1C1-4AD9-B72C-A5EE8724BFA6",
    "exportFormats": [
    ],
    "includedLayerIds": [
    ],
    "layerOptions": 0,
    "shouldTrim": false
  },
  "frame": {
    "_class": "rect",
    "constrainProportions": false,
    "do_objectID": "CEF98579-D0AB-4BFA-8961-A475A0583109",
    "height": 319,
    "width": 3,
    "x": 0,
    "y": 0
  },
  "isClosed": false,
  "isFlippedHorizontal": false,
  "isFlippedVertical": false,
  "isLocked": false,
  "isVisible": true,
  "layerListExpandedType": 0,
  "name": "Path",
  "nameIsFixed": false,
  "pointRadiusBehaviour": 1,
  "points": [
    {
      "_class": "curvePoint",
      "cornerRadius": 0,
      "curveFrom": "{0.66666666666666663, 0.0031347962382445131}",
      "curveMode": 1,
      "curveTo": "{0.66666666666666663, 0.0031347962382445131}",
      "hasCurveFrom": false,
      "hasCurveTo": false,
      "point": "{0.5, 0.0015673981191222566}"
    },
    {
      "_class": "curvePoint",
      "cornerRadius": 0,
      "curveFrom": "{1, 0.0062695924764890262}",
      "curveMode": 1,
      "curveTo": "{1, 0.0062695924764890262}",
      "hasCurveFrom": false,
      "hasCurveTo": false,
      "point": "{0.5, 0.99843260188087768}"
    }
  ],
  "resizingConstraint": 63,
  "resizingType": 0,
  "rotation": 0,
  "shouldBreakMaskChain": false
}