{
  "_class": "group",
  "do_objectID": "4BA1D955-E20D-4777-8DAC-73E4764A9187",
  "exportOptions": {
    "_class": "exportOptions",
    "do_objectID": "3ED0CE7F-80D5-42E8-82F9-A0B0BC1D1614",
    "exportFormats": [
    ],
    "includedLayerIds": [
    ],
    "layerOptions": 0,
    "shouldTrim": false
  },
  "frame": {
    "_class": "rect",
    "constrainProportions": false,
    "do_objectID": "E002652F-6A08-4D55-9983-C2C1D949D33C",
    "height": 5,
    "width": 30,
    "x": 0,
    "y": 19.85982421875
  },
  "hasClickThrough": false,
  "isFlippedHorizontal": false,
  "isFlippedVertical": false,
  "isLocked": false,
  "isVisible": true,
  "layerListExpandedType": 2,
  "layers": [
    {
      "class": "shapeGroup",
      "id": "8AEB20B6-B7A1-42B4-8F03-DF5CA6122C35"
    },
    {
      "class": "shapeGroup",
      "id": "883CE0CE-65F3-4F28-849A-B9757D217799"
    }
  ],
  "name": "Group 9",
  "nameIsFixed": false,
  "resizingConstraint": 63,
  "resizingType": 0,
  "rotation": 0,
  "shouldBreakMaskChain": false,
  "style": {
    "_class": "style",
    "do_objectID": "8238BA90-A279-4FBD-8654-BFE7CB261F1E",
    "endDecorationType": 0,
    "miterLimit": 10,
    "startDecorationType": 0
  }
}