{
  "_class": "shapeGroup",
  "clippingMaskMode": 0,
  "do_objectID": "66F09F43-2FDE-4438-8329-E03BED26B118",
  "exportOptions": {
    "_class": "exportOptions",
    "do_objectID": "DC4AA9DF-D730-44E1-BEC7-EB08771C1AC3",
    "exportFormats": [
    ],
    "includedLayerIds": [
    ],
    "layerOptions": 0,
    "shouldTrim": false
  },
  "frame": {
    "_class": "rect",
    "constrainProportions": false,
    "do_objectID": "4734ABDF-C258-43A4-AD36-7CDC0BC63F3C",
    "height": 61,
    "width": 1134,
    "x": 0,
    "y": 0
  },
  "hasClickThrough": false,
  "hasClippingMask": false,
  "isFlippedHorizontal": false,
  "isFlippedVertical": false,
  "isLocked": false,
  "isVisible": true,
  "layerListExpandedType": 0,
  "layers": [
    {
      "class": "rectangle",
      "id": "A42C8784-3F45-4E34-8CB7-740B49ADF000"
    }
  ],
  "name": "Rectangle 8",
  "nameIsFixed": false,
  "resizingConstraint": 63,
  "resizingType": 0,
  "rotation": 0,
  "shouldBreakMaskChain": false,
  "style": {
    "_class": "style",
    "borders": [
      {
        "_class": "border",
        "color": {
          "_class": "color",
          "alpha": 1,
          "blue": 0.8785342261904762,
          "green": 0.8785342261904762,
          "red": 0.8785342261904762
        },
        "fillType": 0,
        "isEnabled": true,
        "position": 1,
        "thickness": 1
      }
    ],
    "do_objectID": "55EE3370-8233-4FC8-A58B-088F9CC85B15",
    "endDecorationType": 0,
    "fills": [
      {
        "_class": "fill",
        "color": {
          "_class": "color",
          "alpha": 1,
          "blue": 0.847,
          "green": 0.847,
          "red": 0.847
        },
        "fillType": 0,
        "isEnabled": false,
        "noiseIndex": 0,
        "noiseIntensity": 0,
        "patternFillType": 1,
        "patternTileScale": 1
      }
    ],
    "miterLimit": 10,
    "startDecorationType": 0
  },
  "userInfo": {
    "com.animaapp.stc-sketch-plugin": {
      "kModelPropertiesKey": {
      }
    }
  },
  "windingRule": 1
}