{
  "_class": "text",
  "attributedString": {
    "_class": "attributedString",
    "attributes": [
      {
        "_class": "stringAttribute",
        "attributes": {
          "MSAttributedStringColorAttribute": {
            "_class": "color",
            "alpha": 1,
            "blue": 0.4,
            "green": 0.4,
            "red": 0.4
          },
          "MSAttributedStringFontAttribute": {
            "_class": "fontDescriptor",
            "attributes": {
              "name": "OpenSans-Regular",
              "size": 19.20000076293945
            }
          },
          "paragraphStyle": {
            "_class": "paragraphStyle",
            "maximumLineHeight": 19.20000076293945,
            "minimumLineHeight": 19.20000076293945
          },
          "textStyleVerticalAlignmentKey": 0
        },
        "length": 9,
        "location": 0
      }
    ],
    "string": "Objetivos"
  },
  "automaticallyDrawOnUnderlyingPath": false,
  "do_objectID": "A9F3DD09-3131-4959-8C7A-F9F5EC0CAF90",
  "dontSynchroniseWithSymbol": false,
  "exportOptions": {
    "_class": "exportOptions",
    "do_objectID": "BAAE5F9D-A411-43A0-89E8-DBBABE4BB753",
    "exportFormats": [
    ],
    "includedLayerIds": [
    ],
    "layerOptions": 0,
    "shouldTrim": false
  },
  "frame": {
    "_class": "rect",
    "constrainProportions": false,
    "do_objectID": "F32CE907-B5E1-401C-ACA9-2F0F514333C4",
    "height": 20,
    "width": 85,
    "x": 291,
    "y": 0
  },
  "glyphBounds": "{{1, 2}, {83, 20}}",
  "isFlippedHorizontal": false,
  "isFlippedVertical": false,
  "isLocked": false,
  "isVisible": true,
  "layerListExpandedType": 0,
  "lineSpacingBehaviour": 2,
  "name": "Objetivos",
  "nameIsFixed": false,
  "resizingConstraint": 47,
  "resizingType": 0,
  "rotation": 0,
  "shouldBreakMaskChain": false,
  "style": {
    "_class": "style",
    "do_objectID": "E506FD27-1C93-4CD7-BACC-48562D2EF9C1",
    "endDecorationType": 0,
    "miterLimit": 10,
    "sharedObjectID": "89FB4361-AF60-4C0A-947C-D8BAB7A4C5F8",
    "startDecorationType": 0,
    "textStyle": {
      "_class": "textStyle",
      "do_objectID": "27F982BC-455B-453F-BA9A-31E10903B1A6",
      "encodedAttributes": {
        "MSAttributedStringColorAttribute": {
          "_class": "color",
          "alpha": 1,
          "blue": 0.4,
          "green": 0.4,
          "red": 0.4
        },
        "MSAttributedStringFontAttribute": {
          "_class": "fontDescriptor",
          "attributes": {
            "name": "OpenSans-Regular",
            "size": 19.20000076293945
          }
        },
        "paragraphStyle": {
          "_class": "paragraphStyle",
          "maximumLineHeight": 19.20000076293945,
          "minimumLineHeight": 19.20000076293945
        },
        "textStyleVerticalAlignmentKey": 0
      },
      "verticalAlignment": 0
    }
  },
  "textBehaviour": 0,
  "userInfo": {
    "com.animaapp.stc-sketch-plugin": {
      "kModelPropertiesKey": {
        "isAutoWidth": 1
      }
    }
  }
}