{
  "_class": "group",
  "do_objectID": "81B99559-6A55-4376-8D4C-95E5373D159E",
  "exportOptions": {
    "_class": "exportOptions",
    "do_objectID": "5DC8F7F1-14F8-42AB-982F-0E49C0F6B523",
    "exportFormats": [
    ],
    "includedLayerIds": [
    ],
    "layerOptions": 0,
    "shouldTrim": false
  },
  "frame": {
    "_class": "rect",
    "constrainProportions": false,
    "do_objectID": "D9B79134-3216-402C-9D3D-BE6125165906",
    "height": 351,
    "width": 1088,
    "x": 223,
    "y": 509
  },
  "hasClickThrough": false,
  "isFlippedHorizontal": false,
  "isFlippedVertical": false,
  "isLocked": false,
  "isVisible": true,
  "layerListExpandedType": 2,
  "layers": [
    {
      "class": "text",
      "id": "94C4CD1E-9C3F-4D83-962A-85430CC2924E"
    }
  ],
  "name": "objetivo1 copy",
  "nameIsFixed": true,
  "resizingConstraint": 63,
  "resizingType": 0,
  "rotation": 0,
  "shouldBreakMaskChain": false,
  "style": {
    "_class": "style",
    "do_objectID": "B18DBE61-051E-40A0-B558-FA3E1AF5921D",
    "endDecorationType": 0,
    "miterLimit": 10,
    "startDecorationType": 0
  },
  "userInfo": {
    "com.animaapp.stc-sketch-plugin": {
      "kModelPropertiesKey": {
      }
    }
  }
}