{
  "_class": "symbolInstance",
  "do_objectID": "C0E4F063-1145-46F1-8EEF-084147E70464",
  "exportOptions": {
    "_class": "exportOptions",
    "do_objectID": "01E76CD3-ED43-441E-B99F-99307D5CA4DA",
    "exportFormats": [
    ],
    "includedLayerIds": [
    ],
    "layerOptions": 0,
    "shouldTrim": false
  },
  "frame": {
    "_class": "rect",
    "constrainProportions": false,
    "do_objectID": "3CF5C314-790B-4C99-A5A7-954E955093BA",
    "height": 24,
    "width": 24,
    "x": 388,
    "y": 6
  },
  "horizontalSpacing": 0,
  "isFlippedHorizontal": false,
  "isFlippedVertical": false,
  "isLocked": false,
  "isVisible": true,
  "layerListExpandedType": 0,
  "name": "IC_arrow-down",
  "nameIsFixed": false,
  "overrideValues": [
  ],
  "resizingConstraint": 63,
  "resizingType": 0,
  "rotation": 0,
  "scale": 1,
  "shouldBreakMaskChain": false,
  "style": {
    "_class": "style",
    "do_objectID": "4EF9F8F1-7738-4072-A10D-BB56484037EE",
    "endDecorationType": 0,
    "miterLimit": 10,
    "startDecorationType": 0
  },
  "symbolID": "0960F5C7-2CEB-4D53-8D20-B4EA1C98D508",
  "userInfo": {
    "com.animaapp.stc-sketch-plugin": {
      "kModelPropertiesKey": {
      }
    }
  },
  "verticalSpacing": 0
}