{
  "_class": "group",
  "do_objectID": "379C3F9D-5A1A-43BD-A02C-D7909DCE179A",
  "exportOptions": {
    "_class": "exportOptions",
    "do_objectID": "92B896C3-922B-423C-8A44-EE3FA7910BA7",
    "exportFormats": [
    ],
    "includedLayerIds": [
    ],
    "layerOptions": 0,
    "shouldTrim": false
  },
  "frame": {
    "_class": "rect",
    "constrainProportions": false,
    "do_objectID": "04B32DC2-E99A-4229-A144-1B719C353F7A",
    "height": 105,
    "width": 1092,
    "x": 227,
    "y": 360
  },
  "hasClickThrough": false,
  "isFlippedHorizontal": false,
  "isFlippedVertical": false,
  "isLocked": false,
  "isVisible": true,
  "layerListExpandedType": 2,
  "layers": [
    {
      "class": "text",
      "id": "56D6F875-7190-47B0-AC6E-04BAFF2CBC14"
    },
    {
      "class": "text",
      "id": "FE454AA7-DE49-44D3-A64B-C2A3CF9BF964"
    }
  ],
  "name": "objetivo1",
  "nameIsFixed": true,
  "resizingConstraint": 63,
  "resizingType": 0,
  "rotation": 0,
  "shouldBreakMaskChain": false,
  "style": {
    "_class": "style",
    "do_objectID": "F121C4C9-C829-4D1E-B6E2-8E8BE85E3871",
    "endDecorationType": 0,
    "miterLimit": 10,
    "startDecorationType": 0
  },
  "userInfo": {
    "com.animaapp.stc-sketch-plugin": {
      "kModelPropertiesKey": {
      }
    }
  }
}