{
  "_class": "shapeGroup",
  "clippingMaskMode": 0,
  "do_objectID": "790290C6-ECA9-4BFF-97F6-943130E46954",
  "exportOptions": {
    "_class": "exportOptions",
    "do_objectID": "FE4E9AD3-3D2B-4A66-89A1-73BF60E7DF84",
    "exportFormats": [
    ],
    "includedLayerIds": [
    ],
    "layerOptions": 0,
    "shouldTrim": false
  },
  "frame": {
    "_class": "rect",
    "constrainProportions": true,
    "do_objectID": "EE6C3687-7736-443A-A145-E4A50C40C07D",
    "height": 24,
    "width": 24,
    "x": 4.970562748476368,
    "y": 4.97056274847705
  },
  "hasClickThrough": false,
  "hasClippingMask": false,
  "isFlippedHorizontal": false,
  "isFlippedVertical": false,
  "isLocked": false,
  "isVisible": true,
  "layerListExpandedType": 1,
  "layers": [
    {
      "class": "shapePath",
      "id": "897E95D7-CC85-48E5-8B95-3BAEDB41CFFC"
    },
    {
      "class": "shapePath",
      "id": "1357DD80-0F53-48C3-B98C-BD52108C7A20"
    },
    {
      "class": "shapePath",
      "id": "97ADA55F-DA6C-4C10-9677-8B8BAA679C27"
    }
  ],
  "name": "cancel-1",
  "nameIsFixed": true,
  "resizingConstraint": 63,
  "resizingType": 0,
  "rotation": 315,
  "shouldBreakMaskChain": false,
  "style": {
    "_class": "style",
    "blur": {
      "_class": "blur",
      "center": "{0.5, 0.5}",
      "do_objectID": "7D90C9B1-A9C1-45C7-B4A1-8FF3CCAB2812",
      "isEnabled": false,
      "motionAngle": 0,
      "radius": 4.36988092897125,
      "type": 0
    },
    "do_objectID": "E7DA5595-E669-4E14-B67F-7ED6B8731504",
    "endDecorationType": 0,
    "fills": [
      {
        "_class": "fill",
        "color": {
          "_class": "color",
          "alpha": 1,
          "blue": 1,
          "green": 1,
          "red": 1
        },
        "fillType": 0,
        "isEnabled": true,
        "noiseIndex": 0,
        "noiseIntensity": 0,
        "patternFillType": 1,
        "patternTileScale": 1
      }
    ],
    "miterLimit": 10,
    "startDecorationType": 0
  },
  "userInfo": {
    "com.animaapp.stc-sketch-plugin": {
      "kModelPropertiesKey": {
        "constraints": {
          "aspectRatio": {
            "constant": 24,
            "enabled": 1,
            "modelID": "constraint_e9ba9c06-db5e-4415-9385-56741839e5a4",
            "model_class": "ADModelConstraint",
            "model_version": 0.1,
            "multiplier": 24
          },
          "automatic": 1,
          "modelID": "viewConstraints_107a198a-d83f-4954-9d80-74447b7c1e7d",
          "model_class": "ADModelViewConstraints",
          "model_version": 0.1,
          "scaleFactor": 1
        }
      }
    }
  },
  "windingRule": 1
}