{
  "_class": "group",
  "do_objectID": "CDAAB1B2-E466-43C0-AD7B-0AA4A95E51CD",
  "exportOptions": {
    "_class": "exportOptions",
    "do_objectID": "DC637BBA-36E6-4F3C-9E03-70044F5F7A6F",
    "exportFormats": [
    ],
    "includedLayerIds": [
    ],
    "layerOptions": 0,
    "shouldTrim": false
  },
  "frame": {
    "_class": "rect",
    "constrainProportions": false,
    "do_objectID": "E0E1A847-15D4-4C3E-B333-4FC9B9A1A277",
    "height": 44.59459459459459,
    "width": 56,
    "x": 0,
    "y": 0.196216216216214
  },
  "hasClickThrough": false,
  "isFlippedHorizontal": false,
  "isFlippedVertical": false,
  "isLocked": false,
  "isVisible": true,
  "layerListExpandedType": 0,
  "layers": [
    {
      "class": "shapeGroup",
      "id": "D4EAD41E-BBEB-4AFC-8C17-BC349DAE971F"
    },
    {
      "class": "shapeGroup",
      "id": "29C8B501-7439-4276-84A8-A172BE6E84D7"
    }
  ],
  "name": "Group 3",
  "nameIsFixed": false,
  "resizingConstraint": 63,
  "resizingType": 0,
  "rotation": 0,
  "shouldBreakMaskChain": false,
  "style": {
    "_class": "style",
    "blur": {
      "_class": "blur",
      "center": "{0.5, 0.5}",
      "do_objectID": "BF67B743-5D1F-468B-99C5-40F56DDCB0C4",
      "isEnabled": false,
      "motionAngle": 0,
      "radius": 4,
      "type": 0
    },
    "do_objectID": "0B364C58-2452-4DF4-8200-B51E03DDA9C2",
    "endDecorationType": 0,
    "miterLimit": 10,
    "startDecorationType": 0
  },
  "userInfo": {
    "com.animaapp.stc-sketch-plugin": {
      "kModelPropertiesKey": {
      }
    }
  }
}